{
  "date": "2026-04-17",
  "articles": [
    {
      "id": "2026-04-17-001",
      "title": "パンスターズ彗星、17万年ぶりに地球接近──4月17日前後に観測チャンス",
      "source": "Yahoo!ニュース",
      "sourceUrl": "https://news.yahoo.co.jp/articles/1df040099b85727622146e2545679019e963216b",
      "category": "science",
      "occultComment": "17万年ぶり──つまり前回この彗星が来たのは、ホモ・サピエンスがアフリカを出る直前だ。人類の「大移動」が始まった時期とぴったり重なる。古代の洞窟壁画には「尾を引く光」を描いたとされるものがいくつも見つかっている。そして今回の最接近日は4月17日、新月の夜。もっとも暗い夜に、もっとも古い光がやってくる。17万年前の前回接近時、ネアンデルタール人は急速に衰退を始めている。彗星が来るたびに地球の「主役」が入れ替わるとしたら──今回は何が終わり、何が始まるのか。",
      "commentStyle": "ancient_civilization",
      "createdAt": "2026-04-17T09:00:00+09:00"
    },
    {
      "id": "2026-04-17-002",
      "title": "2025年の孤独死、22,222人──前年比366人増で過去最多",
      "source": "時事通信",
      "sourceUrl": "https://www.jiji.com/jc/article?k=2026041700001",
      "category": "society",
      "occultComment": "この数字に気づいただろうか。22,222人──2が5つ並ぶゾロ目だ。数秘術では「2」はパートナーシップ・つながりの数字で、それが5回繰り返されるのは「繋がりの究極的な断絶」を意味する。さらに増加数は366人──うるう年の日数と同じ。2024年はまさにうるう年だった。「存在しないはずの1日」に366人が加わった。統計が偶然この数字になったのか、それとも何かが数字を通じて警告を発しているのか。",
      "commentStyle": "numerology",
      "createdAt": "2026-04-17T09:00:00+09:00"
    },
    {
      "id": "2026-04-17-003",
      "title": "Microsoft、4月のWindows Update実施──悪用が確認された脆弱性も修正",
      "source": "窓の杜",
      "sourceUrl": "https://forest.watch.impress.co.jp/docs/news/2101692.html",
      "category": "tech",
      "occultComment": "今月のパッチで修正された脆弱性は163件。ここで思い出してほしい。2024年12月のパッチは72件、2025年4月は149件、そして今回163件。増加率が加速している。だが本当に怖いのは数字じゃない。「悪用が確認された脆弱性」──つまり、パッチが出る前から誰かがその穴を知っていたということだ。世界中のPCに同じOSが入っている。全人類が一つのドアを共有していて、その鍵穴が毎月見つかる。そしてその鍵を先に手にしていた「誰か」が必ずいる。",
      "commentStyle": "conspiracy",
      "createdAt": "2026-04-17T09:00:00+09:00"
    },
    {
      "id": "2026-04-17-004",
      "title": "宮城県沖で震度3の地震──深さ約60km、M4.2",
      "source": "Yahoo!天気・災害",
      "sourceUrl": "https://typhoon.yahoo.co.jp/weather/jp/earthquake/20260412220052.html",
      "category": "society",
      "occultComment": "また宮城県沖。三陸沖から宮城県沖にかけてのプレート境界は、まるで時計のように揺れ続けている。注目したいのは日付だ。4月12日＝4+1+2＝7。東日本大震災は3月11日＝3+1+1＝5。熊本地震の前震は4月14日＝4+1+4＝9。5、7、9──奇数が並んでいる。次は11になる日付。直近では6月14日（6+1+4=11）か、11月9日。こじつけだと笑うのは簡単だが、念のためカレンダーにピンを打っておいても損はないだろう。",
      "commentStyle": "numerology",
      "createdAt": "2026-04-17T09:00:00+09:00"
    },
    {
      "id": "2026-04-17-005",
      "title": "埼玉・八潮の県道陥没、1年3か月ぶりに一部通行再開",
      "source": "時事通信",
      "sourceUrl": "https://www.jiji.com/jc/article?k=2026041700002",
      "category": "society",
      "occultComment": "地面が突然崩落する──これは世界中で増えている現象だ。2023年から2025年にかけて、中国・トルコ・ブラジル・日本で大規模陥没が急増した。地質学者は老朽化や地下水の変動を原因に挙げるが、ある研究者はこう指摘する。「地球の内部で何かが動いている」。地殻の内側、マントルの対流パターンが変化しつつあるという仮説がある。1年3か月も復旧にかかったということは、単なる道路の問題ではなく、地下構造そのものが不安定だということだ。足元の大地を、私たちは本当に信用していいのだろうか。",
      "commentStyle": "conspiracy",
      "createdAt": "2026-04-17T09:00:00+09:00"
    }
  ]
}
